CHANGELOG.md
MANIFEST.in
README.md
setup.cfg
setup.py
versioneer.py
src/libreflow/__init__.py
src/libreflow.extensions.anpo.export_illustrator.egg-info/PKG-INFO
src/libreflow.extensions.anpo.export_illustrator.egg-info/SOURCES.txt
src/libreflow.extensions.anpo.export_illustrator.egg-info/dependency_links.txt
src/libreflow.extensions.anpo.export_illustrator.egg-info/top_level.txt
src/libreflow/extensions/__init__.py
src/libreflow/extensions/anpo/__init__.py
src/libreflow/extensions/anpo/export_illustrator/__init__.py
src/libreflow/extensions/anpo/export_illustrator/_version.py
src/libreflow/extensions/anpo/export_illustrator/scripts/__init__.py
src/libreflow/extensions/anpo/export_illustrator/scripts/layers2png.jsx